savefile/__init__.py
saveFile-0.0.1.dist-info/LICENSE
saveFile-0.0.1.dist-info/METADATA
saveFile-0.0.1.dist-info/WHEEL
saveFile-0.0.1.dist-info/top_level.txt
saveFile-0.0.1.dist-info/RECORD
