Metadata-Version: 2.1
Name: saveFile
Version: 0.0.1
Summary: Thread Save Text Files
Home-page: https://github.com/pypa/sampleproject
Author: Save File
Author-email: author@example.com
Project-URL: Bug Tracker, https://github.com/pypa/sampleproject/issues
Classifier: Programming Language :: Python :: 3
Classifier: License :: OSI Approved :: MIT License
Classifier: Operating System :: OS Independent
Requires-Python: >=3.6
License-File: LICENSE
